{
  "metadata": {
    "configurationVersions": [
      7
    ],
    "clusterVersion": "1.291.99.20240515-061005"
  },
  "dashboardMetadata": {
    "name": "KIWI-F2F",
    "shared": true,
    "owner": "madan.karuppiah@digital.cabinet-office.gov.uk",
    "hasConsistentColors": false
  },
  "tiles": [
    {
      "name": "F2F Lambda Errors",
      "tileType": "DATA_EXPLORER",
      "configured": true,
      "bounds": {
        "top": 76,
        "left": 0,
        "width": 532,
        "height": 304
      },
      "tileFilter": {},
      "isAutoRefreshDisabled": false,
      "customName": "Data explorer results",
      "queries": [
        {
          "id": "A",
          "spaceAggregation": "AUTO",
          "timeAggregation": "DEFAULT",
          "splitBy": [
            "dt.entity.aws_lambda_function"
          ],
          "metricSelector": "builtin:cloud.aws.lambda.errors:filter(and(or(in(\"dt.entity.aws_lambda_function\",entitySelector(\"type(aws_lambda_function),entityName.equals(~\"F2F-SessionConfig-f2f-cri-api~\")\")),in(\"dt.entity.aws_lambda_function\",entitySelector(\"type(aws_lambda_function),entityName.equals(~\"F2F-ThankYouEmail-f2f-cri-api~\")\")),in(\"dt.entity.aws_lambda_function\",entitySelector(\"type(aws_lambda_function),entityName.equals(~\"Document-Selection-f2f-cri-api~\")\")),in(\"dt.entity.aws_lambda_function\",entitySelector(\"type(aws_lambda_function),entityName.equals(~\"F2F-Session-f2f-cri-api~\")\")),in(\"dt.entity.aws_lambda_function\",entitySelector(\"type(aws_lambda_function),entityName.equals(~\"F2F-Authorization-f2f-cri-api~\")\")),in(\"dt.entity.aws_lambda_function\",entitySelector(\"type(aws_lambda_function),entityName.equals(~\"User-Info-f2f-cri-api~\")\")),in(\"dt.entity.aws_lambda_function\",entitySelector(\"type(aws_lambda_function),entityName.equals(~\"Access-Token-f2f-cri-api~\")\")),in(\"dt.entity.aws_lambda_function\",entitySelector(\"type(aws_lambda_function),entityName.equals(~\"Abort-f2f-cri-api~\")\")),in(\"dt.entity.aws_lambda_function\",entitySelector(\"type(aws_lambda_function),entityName.equals(~\"JsonWebKeys-f2f-cri-api~\")\")),in(\"dt.entity.aws_lambda_function\",entitySelector(\"type(aws_lambda_function),entityName.equals(~\"F2F-YotiCallback-f2f-cri-api~\")\")),in(\"dt.entity.aws_lambda_function\",entitySelector(\"type(aws_lambda_function),entityName.equals(~\"F2F-ReminderEmail-f2f-cri-api~\")\")),in(\"dt.entity.aws_lambda_function\",entitySelector(\"type(aws_lambda_function),entityName.equals(~\"F2F-GovNotify-f2f-cri-api~\")\")),in(\"dt.entity.aws_lambda_function\",entitySelector(\"type(aws_lambda_function),entityName.equals(~\"F2F-TriggerYotiCallbackStateMachine-f2f-cri-api~\")\"))))):splitBy(\"dt.entity.aws_lambda_function\"):sort(value(auto,descending)):limit(20)",
          "rate": "NONE",
          "enabled": true
        }
      ],
      "visualConfig": {
        "type": "PIE_CHART",
        "global": {},
        "rules": [
          {
            "matcher": "A:",
            "unitTransform": "auto",
            "valueFormat": "auto",
            "properties": {
              "color": "DEFAULT",
              "seriesType": "STACKED_COLUMN"
            },
            "seriesOverrides": [
              {
                "name": "Select series",
                "color": "#c9a000"
              },
              {
                "name": "Select series",
                "color": "#1f7e1e"
              },
              {
                "name": "Select series",
                "color": "#93060e"
              }
            ]
          }
        ],
        "axes": {
          "xAxis": {
            "visible": true
          },
          "yAxes": []
        },
        "heatmapSettings": {
          "yAxis": "VALUE"
        },
        "thresholds": [
          {
            "axisTarget": "LEFT",
            "rules": [
              {
                "color": "#7dc540"
              },
              {
                "color": "#f5d30f"
              },
              {
                "color": "#dc172a"
              }
            ],
            "visible": true
          }
        ],
        "tableSettings": {
          "hiddenColumns": []
        },
        "graphChartSettings": {
          "connectNulls": false
        },
        "honeycombSettings": {
          "showHive": true,
          "showLegend": true,
          "showLabels": false
        }
      },
      "queriesSettings": {
        "resolution": ""
      },
      "metricExpressions": [
        "resolution=Inf&(builtin:cloud.aws.lambda.errors:filter(and(or(in(\"dt.entity.aws_lambda_function\",entitySelector(\"type(aws_lambda_function),entityName.equals(~\"F2F-SessionConfig-f2f-cri-api~\")\")),in(\"dt.entity.aws_lambda_function\",entitySelector(\"type(aws_lambda_function),entityName.equals(~\"F2F-ThankYouEmail-f2f-cri-api~\")\")),in(\"dt.entity.aws_lambda_function\",entitySelector(\"type(aws_lambda_function),entityName.equals(~\"Document-Selection-f2f-cri-api~\")\")),in(\"dt.entity.aws_lambda_function\",entitySelector(\"type(aws_lambda_function),entityName.equals(~\"F2F-Session-f2f-cri-api~\")\")),in(\"dt.entity.aws_lambda_function\",entitySelector(\"type(aws_lambda_function),entityName.equals(~\"F2F-Authorization-f2f-cri-api~\")\")),in(\"dt.entity.aws_lambda_function\",entitySelector(\"type(aws_lambda_function),entityName.equals(~\"User-Info-f2f-cri-api~\")\")),in(\"dt.entity.aws_lambda_function\",entitySelector(\"type(aws_lambda_function),entityName.equals(~\"Access-Token-f2f-cri-api~\")\")),in(\"dt.entity.aws_lambda_function\",entitySelector(\"type(aws_lambda_function),entityName.equals(~\"Abort-f2f-cri-api~\")\")),in(\"dt.entity.aws_lambda_function\",entitySelector(\"type(aws_lambda_function),entityName.equals(~\"JsonWebKeys-f2f-cri-api~\")\")),in(\"dt.entity.aws_lambda_function\",entitySelector(\"type(aws_lambda_function),entityName.equals(~\"F2F-YotiCallback-f2f-cri-api~\")\")),in(\"dt.entity.aws_lambda_function\",entitySelector(\"type(aws_lambda_function),entityName.equals(~\"F2F-ReminderEmail-f2f-cri-api~\")\")),in(\"dt.entity.aws_lambda_function\",entitySelector(\"type(aws_lambda_function),entityName.equals(~\"F2F-GovNotify-f2f-cri-api~\")\")),in(\"dt.entity.aws_lambda_function\",entitySelector(\"type(aws_lambda_function),entityName.equals(~\"F2F-TriggerYotiCallbackStateMachine-f2f-cri-api~\")\"))))):splitBy(\"dt.entity.aws_lambda_function\"):sort(value(auto,descending)):limit(20)):limit(100):names"
      ]
    },
    {
      "name": "F2F Lambda Function Invocations",
      "tileType": "DATA_EXPLORER",
      "configured": true,
      "bounds": {
        "top": 76,
        "left": 532,
        "width": 1026,
        "height": 304
      },
      "tileFilter": {},
      "isAutoRefreshDisabled": false,
      "customName": "Data explorer results",
      "queries": [
        {
          "id": "A",
          "metric": "builtin:cloud.aws.lambda.invocations",
          "spaceAggregation": "AUTO",
          "timeAggregation": "DEFAULT",
          "splitBy": [
            "dt.entity.aws_lambda_function"
          ],
          "sortBy": "DESC",
          "sortByDimension": "",
          "filterBy": {
            "filterOperator": "AND",
            "nestedFilters": [
              {
                "filter": "dt.entity.aws_lambda_function",
                "filterType": "NAME",
                "filterOperator": "OR",
                "entityAttribute": "entityName",
                "nestedFilters": [],
                "criteria": [
                  {
                    "value": "F2F-Session-f2f-cri-api",
                    "evaluator": "IN",
                    "matchExactly": true
                  },
                  {
                    "value": "F2F-TriggerYotiCallbackStateMachine-f2f-cri-api",
                    "evaluator": "IN",
                    "matchExactly": true
                  },
                  {
                    "value": "Access-Token-f2f-cri-api",
                    "evaluator": "IN",
                    "matchExactly": true
                  },
                  {
                    "value": "F2F-ReminderEmail-f2f-cri-api",
                    "evaluator": "IN",
                    "matchExactly": true
                  },
                  {
                    "value": "Document-Selection-f2f-cri-api",
                    "evaluator": "IN",
                    "matchExactly": true
                  },
                  {
                    "value": "Abort-f2f-cri-api",
                    "evaluator": "IN",
                    "matchExactly": true
                  },
                  {
                    "value": "F2F-GovNotify-f2f-cri-api",
                    "evaluator": "IN",
                    "matchExactly": true
                  },
                  {
                    "value": "F2F-ThankYouEmail-f2f-cri-api",
                    "evaluator": "IN",
                    "matchExactly": true
                  },
                  {
                    "value": "JsonWebKeys-f2f-cri-api",
                    "evaluator": "IN",
                    "matchExactly": true
                  },
                  {
                    "value": "User-Info-f2f-cri-api",
                    "evaluator": "IN",
                    "matchExactly": true
                  },
                  {
                    "value": "F2F-SessionConfig-f2f-cri-api",
                    "evaluator": "IN",
                    "matchExactly": true
                  },
                  {
                    "value": "F2F-Authorization-f2f-cri-api",
                    "evaluator": "IN",
                    "matchExactly": true
                  },
                  {
                    "value": "F2F-YotiCallback-f2f-cri-api",
                    "evaluator": "IN",
                    "matchExactly": true
                  }
                ]
              }
            ],
            "criteria": []
          },
          "limit": 20,
          "rate": "NONE",
          "enabled": true
        }
      ],
      "visualConfig": {
        "type": "STACKED_COLUMN",
        "global": {},
        "rules": [
          {
            "matcher": "A:",
            "unitTransform": "auto",
            "valueFormat": "auto",
            "properties": {
              "color": "DEFAULT",
              "seriesType": "STACKED_COLUMN"
            },
            "seriesOverrides": [
              {
                "name": "Select series",
                "color": "#c9a000"
              },
              {
                "name": "Select series",
                "color": "#1f7e1e"
              },
              {
                "name": "Select series",
                "color": "#93060e"
              }
            ]
          }
        ],
        "axes": {
          "xAxis": {
            "displayName": "",
            "visible": true
          },
          "yAxes": [
            {
              "displayName": "",
              "visible": true,
              "min": "AUTO",
              "max": "AUTO",
              "position": "LEFT",
              "queryIds": [
                "A"
              ],
              "defaultAxis": true
            }
          ]
        },
        "heatmapSettings": {
          "yAxis": "VALUE"
        },
        "thresholds": [
          {
            "axisTarget": "LEFT",
            "rules": [
              {
                "color": "#7dc540"
              },
              {
                "color": "#f5d30f"
              },
              {
                "color": "#dc172a"
              }
            ],
            "visible": true
          }
        ],
        "tableSettings": {
          "hiddenColumns": []
        },
        "graphChartSettings": {
          "connectNulls": false
        },
        "honeycombSettings": {
          "showHive": true,
          "showLegend": true,
          "showLabels": false
        }
      },
      "queriesSettings": {
        "resolution": ""
      },
      "metricExpressions": [
        "resolution=null&(builtin:cloud.aws.lambda.invocations:filter(and(or(in(\"dt.entity.aws_lambda_function\",entitySelector(\"type(aws_lambda_function),entityName.equals(~\"F2F-ReminderEmail-f2f-cri-api~\")\")),in(\"dt.entity.aws_lambda_function\",entitySelector(\"type(aws_lambda_function),entityName.equals(~\"F2F-ThankYouEmail-f2f-cri-api~\")\")),in(\"dt.entity.aws_lambda_function\",entitySelector(\"type(aws_lambda_function),entityName.equals(~\"F2F-Session-f2f-cri-api~\")\")),in(\"dt.entity.aws_lambda_function\",entitySelector(\"type(aws_lambda_function),entityName.equals(~\"F2F-TriggerYotiCallbackStateMachine-f2f-cri-api~\")\")),in(\"dt.entity.aws_lambda_function\",entitySelector(\"type(aws_lambda_function),entityName.equals(~\"User-Info-f2f-cri-api~\")\")),in(\"dt.entity.aws_lambda_function\",entitySelector(\"type(aws_lambda_function),entityName.equals(~\"Access-Token-f2f-cri-api~\")\")),in(\"dt.entity.aws_lambda_function\",entitySelector(\"type(aws_lambda_function),entityName.equals(~\"F2F-Authorization-f2f-cri-api~\")\")),in(\"dt.entity.aws_lambda_function\",entitySelector(\"type(aws_lambda_function),entityName.equals(~\"Abort-f2f-cri-api~\")\")),in(\"dt.entity.aws_lambda_function\",entitySelector(\"type(aws_lambda_function),entityName.equals(~\"JsonWebKeys-f2f-cri-api~\")\")),in(\"dt.entity.aws_lambda_function\",entitySelector(\"type(aws_lambda_function),entityName.equals(~\"F2F-YotiCallback-f2f-cri-api~\")\")),in(\"dt.entity.aws_lambda_function\",entitySelector(\"type(aws_lambda_function),entityName.equals(~\"Document-Selection-f2f-cri-api~\")\")),in(\"dt.entity.aws_lambda_function\",entitySelector(\"type(aws_lambda_function),entityName.equals(~\"F2F-GovNotify-f2f-cri-api~\")\")),in(\"dt.entity.aws_lambda_function\",entitySelector(\"type(aws_lambda_function),entityName.equals(~\"F2F-SessionConfig-f2f-cri-api~\")\"))))):splitBy(\"dt.entity.aws_lambda_function\"):sort(value(auto,descending)):limit(20)):limit(100):names"
      ]
    },
    {
      "name": "Frontend Request",
      "tileType": "DATA_EXPLORER",
      "configured": true,
      "bounds": {
        "top": 380,
        "left": 1026,
        "width": 304,
        "height": 304
      },
      "tileFilter": {},
      "isAutoRefreshDisabled": false,
      "customName": "Data explorer results",
      "queries": [
        {
          "id": "A",
          "spaceAggregation": "AUTO",
          "timeAggregation": "DEFAULT",
          "splitBy": [
            "dt.entity.service"
          ],
          "metricSelector": "builtin:service.requestCount.total:filter(and(or(in(\"dt.entity.service\",entitySelector(\"type(service),entityName.equals(~\"di-cic-front~\")\"))))):splitBy(\"dt.entity.service\"):sort(value(auto,descending)):limit(20)",
          "rate": "NONE",
          "enabled": true
        }
      ],
      "visualConfig": {
        "type": "SINGLE_VALUE",
        "global": {},
        "rules": [
          {
            "matcher": "A:",
            "properties": {
              "color": "DEFAULT",
              "seriesType": "STACKED_COLUMN"
            },
            "seriesOverrides": []
          }
        ],
        "axes": {
          "xAxis": {
            "visible": true
          },
          "yAxes": []
        },
        "heatmapSettings": {
          "yAxis": "VALUE"
        },
        "thresholds": [
          {
            "axisTarget": "LEFT",
            "rules": [
              {
                "color": "#7dc540"
              },
              {
                "color": "#f5d30f"
              },
              {
                "color": "#dc172a"
              }
            ],
            "visible": true
          }
        ],
        "tableSettings": {
          "hiddenColumns": []
        },
        "graphChartSettings": {
          "connectNulls": false
        },
        "honeycombSettings": {
          "showHive": true,
          "showLegend": true,
          "showLabels": false
        }
      },
      "queriesSettings": {
        "resolution": ""
      },
      "metricExpressions": [
        "resolution=Inf&(builtin:service.requestCount.total:filter(and(or(in(\"dt.entity.service\",entitySelector(\"type(service),entityName.equals(~\"di-cic-front~\")\"))))):splitBy(\"dt.entity.service\"):sort(value(auto,descending)):limit(20)):limit(100):names",
        "resolution=null&(builtin:service.requestCount.total:filter(and(or(in(\"dt.entity.service\",entitySelector(\"type(service),entityName.equals(~\"di-cic-front~\")\"))))):splitBy(\"dt.entity.service\"):sort(value(auto,descending)):limit(20))"
      ]
    },
    {
      "name": "Frontend 4xx Error",
      "tileType": "DATA_EXPLORER",
      "configured": true,
      "bounds": {
        "top": 684,
        "left": 1026,
        "width": 304,
        "height": 304
      },
      "tileFilter": {},
      "isAutoRefreshDisabled": false,
      "customName": "Data explorer results",
      "queries": [
        {
          "id": "A",
          "spaceAggregation": "AUTO",
          "timeAggregation": "DEFAULT",
          "splitBy": [
            "dt.entity.service"
          ],
          "metricSelector": "builtin:service.errors.fourxx.count:filter(and(or(in(\"dt.entity.service\",entitySelector(\"type(service),entityName.equals(~\"di-ipv-cri-f2f-front~\")\"))))):splitBy(\"dt.entity.service\"):sort(value(auto,descending)):limit(20)",
          "rate": "NONE",
          "enabled": true
        }
      ],
      "visualConfig": {
        "type": "SINGLE_VALUE",
        "global": {},
        "rules": [
          {
            "matcher": "A:",
            "unitTransform": "auto",
            "valueFormat": "auto",
            "properties": {
              "color": "DEFAULT",
              "seriesType": "STACKED_COLUMN"
            },
            "seriesOverrides": [
              {
                "name": "Select series",
                "color": "#006bba"
              },
              {
                "name": "di-ipv-cri-f2f-front",
                "color": "#ffe11c"
              },
              {
                "name": "Select series",
                "color": "#9355b7"
              }
            ]
          }
        ],
        "axes": {
          "xAxis": {
            "visible": true
          },
          "yAxes": []
        },
        "heatmapSettings": {
          "yAxis": "VALUE"
        },
        "singleValueSettings": {
          "showTrend": true,
          "showSparkLine": true,
          "linkTileColorToThreshold": true
        },
        "thresholds": [
          {
            "axisTarget": "LEFT",
            "rules": [
              {
                "color": "#7dc540"
              },
              {
                "color": "#f5d30f"
              },
              {
                "color": "#dc172a"
              }
            ],
            "visible": true
          }
        ],
        "tableSettings": {
          "hiddenColumns": []
        },
        "graphChartSettings": {
          "connectNulls": false
        },
        "honeycombSettings": {
          "showHive": true,
          "showLegend": true,
          "showLabels": false
        }
      },
      "queriesSettings": {
        "resolution": ""
      },
      "metricExpressions": [
        "resolution=Inf&(builtin:service.errors.fourxx.count:filter(and(or(in(\"dt.entity.service\",entitySelector(\"type(service),entityName.equals(~\"di-ipv-cri-f2f-front~\")\"))))):splitBy(\"dt.entity.service\"):sort(value(auto,descending)):limit(20)):limit(100):names",
        "resolution=null&(builtin:service.errors.fourxx.count:filter(and(or(in(\"dt.entity.service\",entitySelector(\"type(service),entityName.equals(~\"di-ipv-cri-f2f-front~\")\"))))):splitBy(\"dt.entity.service\"):sort(value(auto,descending)):limit(20))"
      ]
    },
    {
      "name": "Frontend 5xx Error",
      "tileType": "DATA_EXPLORER",
      "configured": true,
      "bounds": {
        "top": 988,
        "left": 1026,
        "width": 304,
        "height": 304
      },
      "tileFilter": {},
      "isAutoRefreshDisabled": false,
      "customName": "Data explorer results",
      "queries": [
        {
          "id": "A",
          "spaceAggregation": "AUTO",
          "timeAggregation": "DEFAULT",
          "splitBy": [
            "dt.entity.service"
          ],
          "metricSelector": "builtin:service.errors.fivexx.count:filter(and(or(in(\"dt.entity.service\",entitySelector(\"type(service),entityName.equals(~\"di-ipv-cri-f2f-front~\")\"))))):splitBy(\"dt.entity.service\"):sort(value(auto,descending)):limit(20)",
          "rate": "NONE",
          "enabled": true
        }
      ],
      "visualConfig": {
        "type": "SINGLE_VALUE",
        "global": {},
        "rules": [
          {
            "matcher": "A:",
            "unitTransform": "auto",
            "valueFormat": "auto",
            "properties": {
              "color": "ROYALBLUE",
              "seriesType": "STACKED_COLUMN"
            },
            "seriesOverrides": [
              {
                "name": "di-ipv-cri-f2f-front",
                "color": "#ffe11c"
              },
              {
                "name": "Select series",
                "color": "#debbf3"
              },
              {
                "name": "Select series",
                "color": "#006d75"
              }
            ]
          }
        ],
        "axes": {
          "xAxis": {
            "visible": true
          },
          "yAxes": []
        },
        "heatmapSettings": {
          "yAxis": "VALUE"
        },
        "singleValueSettings": {
          "showTrend": true,
          "showSparkLine": true,
          "linkTileColorToThreshold": true
        },
        "thresholds": [
          {
            "axisTarget": "LEFT",
            "rules": [
              {
                "color": "#7dc540"
              },
              {
                "color": "#f5d30f"
              },
              {
                "color": "#dc172a"
              }
            ],
            "visible": true
          }
        ],
        "tableSettings": {
          "hiddenColumns": []
        },
        "graphChartSettings": {
          "connectNulls": false
        },
        "honeycombSettings": {
          "showHive": true,
          "showLegend": true,
          "showLabels": false
        }
      },
      "queriesSettings": {
        "resolution": ""
      },
      "metricExpressions": [
        "resolution=Inf&(builtin:service.errors.fivexx.count:filter(and(or(in(\"dt.entity.service\",entitySelector(\"type(service),entityName.equals(~\"di-ipv-cri-f2f-front~\")\"))))):splitBy(\"dt.entity.service\"):sort(value(auto,descending)):limit(20)):limit(100):names",
        "resolution=null&(builtin:service.errors.fivexx.count:filter(and(or(in(\"dt.entity.service\",entitySelector(\"type(service),entityName.equals(~\"di-ipv-cri-f2f-front~\")\"))))):splitBy(\"dt.entity.service\"):sort(value(auto,descending)):limit(20))"
      ]
    },
    {
      "name": "F2F Lambda Function Duration",
      "tileType": "DATA_EXPLORER",
      "configured": true,
      "bounds": {
        "top": 76,
        "left": 1558,
        "width": 418,
        "height": 304
      },
      "tileFilter": {},
      "isAutoRefreshDisabled": false,
      "customName": "Data explorer results",
      "queries": [
        {
          "id": "A",
          "spaceAggregation": "AUTO",
          "timeAggregation": "DEFAULT",
          "splitBy": [
            "dt.entity.aws_lambda_function"
          ],
          "metricSelector": "builtin:cloud.aws.lambda.duration:filter(and(or(in(\"dt.entity.aws_lambda_function\",entitySelector(\"type(aws_lambda_function),entityName.equals(~\"F2F-SessionConfig-f2f-cri-api~\")\")),in(\"dt.entity.aws_lambda_function\",entitySelector(\"type(aws_lambda_function),entityName.equals(~\"F2F-ThankYouEmail-f2f-cri-api~\")\")),in(\"dt.entity.aws_lambda_function\",entitySelector(\"type(aws_lambda_function),entityName.equals(~\"Document-Selection-f2f-cri-api~\")\")),in(\"dt.entity.aws_lambda_function\",entitySelector(\"type(aws_lambda_function),entityName.equals(~\"F2F-Session-f2f-cri-api~\")\")),in(\"dt.entity.aws_lambda_function\",entitySelector(\"type(aws_lambda_function),entityName.equals(~\"F2F-Authorization-f2f-cri-api~\")\")),in(\"dt.entity.aws_lambda_function\",entitySelector(\"type(aws_lambda_function),entityName.equals(~\"Access-Token-f2f-cri-api~\")\")),in(\"dt.entity.aws_lambda_function\",entitySelector(\"type(aws_lambda_function),entityName.equals(~\"User-Info-f2f-cri-api~\")\")),in(\"dt.entity.aws_lambda_function\",entitySelector(\"type(aws_lambda_function),entityName.equals(~\"Abort-f2f-cri-api~\")\")),in(\"dt.entity.aws_lambda_function\",entitySelector(\"type(aws_lambda_function),entityName.equals(~\"JsonWebKeys-f2f-cri-api~\")\")),in(\"dt.entity.aws_lambda_function\",entitySelector(\"type(aws_lambda_function),entityName.equals(~\"F2F-YotiCallback-f2f-cri-api~\")\")),in(\"dt.entity.aws_lambda_function\",entitySelector(\"type(aws_lambda_function),entityName.equals(~\"F2F-ReminderEmail-f2f-cri-api~\")\")),in(\"dt.entity.aws_lambda_function\",entitySelector(\"type(aws_lambda_function),entityName.equals(~\"F2F-GovNotify-f2f-cri-api~\")\")),in(\"dt.entity.aws_lambda_function\",entitySelector(\"type(aws_lambda_function),entityName.equals(~\"F2F-TriggerYotiCallbackStateMachine-f2f-cri-api~\")\"))))):splitBy(\"dt.entity.aws_lambda_function\"):sort(value(auto,descending)):limit(20)",
          "rate": "NONE",
          "enabled": true
        }
      ],
      "visualConfig": {
        "type": "TABLE",
        "global": {},
        "rules": [
          {
            "matcher": "A:",
            "unitTransform": "auto",
            "valueFormat": "auto",
            "properties": {
              "color": "DEFAULT",
              "seriesType": "STACKED_AREA"
            },
            "seriesOverrides": [
              {
                "name": "Select series",
                "color": "#c9a000"
              },
              {
                "name": "Select series",
                "color": "#1f7e1e"
              },
              {
                "name": "Select series",
                "color": "#93060e"
              }
            ]
          }
        ],
        "axes": {
          "xAxis": {
            "visible": true
          },
          "yAxes": []
        },
        "heatmapSettings": {
          "yAxis": "VALUE"
        },
        "thresholds": [
          {
            "axisTarget": "LEFT",
            "columnId": "LambdaFunction code execution time.",
            "rules": [
              {
                "color": "#7dc540"
              },
              {
                "color": "#f5d30f"
              },
              {
                "color": "#dc172a"
              }
            ],
            "queryId": "A",
            "visible": true
          }
        ],
        "tableSettings": {
          "hiddenColumns": [
            "A:dt.entity.aws_lambda_function.name"
          ]
        },
        "graphChartSettings": {
          "connectNulls": false
        },
        "honeycombSettings": {
          "showHive": true,
          "showLegend": true,
          "showLabels": false
        }
      },
      "queriesSettings": {
        "resolution": ""
      },
      "metricExpressions": [
        "resolution=Inf&(builtin:cloud.aws.lambda.duration:filter(and(or(in(\"dt.entity.aws_lambda_function\",entitySelector(\"type(aws_lambda_function),entityName.equals(~\"F2F-SessionConfig-f2f-cri-api~\")\")),in(\"dt.entity.aws_lambda_function\",entitySelector(\"type(aws_lambda_function),entityName.equals(~\"F2F-ThankYouEmail-f2f-cri-api~\")\")),in(\"dt.entity.aws_lambda_function\",entitySelector(\"type(aws_lambda_function),entityName.equals(~\"Document-Selection-f2f-cri-api~\")\")),in(\"dt.entity.aws_lambda_function\",entitySelector(\"type(aws_lambda_function),entityName.equals(~\"F2F-Session-f2f-cri-api~\")\")),in(\"dt.entity.aws_lambda_function\",entitySelector(\"type(aws_lambda_function),entityName.equals(~\"F2F-Authorization-f2f-cri-api~\")\")),in(\"dt.entity.aws_lambda_function\",entitySelector(\"type(aws_lambda_function),entityName.equals(~\"Access-Token-f2f-cri-api~\")\")),in(\"dt.entity.aws_lambda_function\",entitySelector(\"type(aws_lambda_function),entityName.equals(~\"User-Info-f2f-cri-api~\")\")),in(\"dt.entity.aws_lambda_function\",entitySelector(\"type(aws_lambda_function),entityName.equals(~\"Abort-f2f-cri-api~\")\")),in(\"dt.entity.aws_lambda_function\",entitySelector(\"type(aws_lambda_function),entityName.equals(~\"JsonWebKeys-f2f-cri-api~\")\")),in(\"dt.entity.aws_lambda_function\",entitySelector(\"type(aws_lambda_function),entityName.equals(~\"F2F-YotiCallback-f2f-cri-api~\")\")),in(\"dt.entity.aws_lambda_function\",entitySelector(\"type(aws_lambda_function),entityName.equals(~\"F2F-ReminderEmail-f2f-cri-api~\")\")),in(\"dt.entity.aws_lambda_function\",entitySelector(\"type(aws_lambda_function),entityName.equals(~\"F2F-GovNotify-f2f-cri-api~\")\")),in(\"dt.entity.aws_lambda_function\",entitySelector(\"type(aws_lambda_function),entityName.equals(~\"F2F-TriggerYotiCallbackStateMachine-f2f-cri-api~\")\"))))):splitBy(\"dt.entity.aws_lambda_function\"):sort(value(auto,descending)):limit(20)):names"
      ]
    },
    {
      "name": "Frontend 4xx Errors",
      "tileType": "DATA_EXPLORER",
      "configured": true,
      "bounds": {
        "top": 684,
        "left": 1330,
        "width": 646,
        "height": 304
      },
      "tileFilter": {},
      "isAutoRefreshDisabled": false,
      "customName": "Data explorer results",
      "queries": [
        {
          "id": "B",
          "spaceAggregation": "AUTO",
          "timeAggregation": "DEFAULT",
          "splitBy": [
            "dt.entity.service"
          ],
          "metricSelector": "builtin:service.errors.fourxx.rate:filter(and(or(in(\"dt.entity.service\",entitySelector(\"type(service),entityName.equals(~\"di-ipv-cri-f2f-front~\")\")))))",
          "rate": "NONE",
          "enabled": true
        }
      ],
      "visualConfig": {
        "type": "STACKED_COLUMN",
        "global": {},
        "rules": [
          {
            "matcher": "B:",
            "unitTransform": "auto",
            "valueFormat": "auto",
            "properties": {
              "color": "YELLOW",
              "seriesType": "STACKED_COLUMN"
            },
            "seriesOverrides": []
          }
        ],
        "axes": {
          "xAxis": {
            "displayName": "",
            "visible": true
          },
          "yAxes": [
            {
              "displayName": "",
              "visible": true,
              "min": "AUTO",
              "max": "AUTO",
              "position": "LEFT",
              "queryIds": [
                "A"
              ],
              "defaultAxis": true
            },
            {
              "displayName": "",
              "visible": true,
              "min": "AUTO",
              "max": "AUTO",
              "position": "RIGHT",
              "queryIds": [
                "B",
                "C"
              ],
              "defaultAxis": true
            }
          ]
        },
        "heatmapSettings": {
          "yAxis": "VALUE"
        },
        "thresholds": [
          {
            "axisTarget": "LEFT",
            "rules": [
              {
                "color": "#7dc540"
              },
              {
                "color": "#f5d30f"
              },
              {
                "color": "#dc172a"
              }
            ],
            "visible": true
          }
        ],
        "tableSettings": {
          "hiddenColumns": []
        },
        "graphChartSettings": {
          "connectNulls": false
        },
        "honeycombSettings": {
          "showHive": true,
          "showLegend": true,
          "showLabels": false
        }
      },
      "queriesSettings": {
        "resolution": ""
      },
      "metricExpressions": [
        "resolution=null&(builtin:service.errors.fourxx.rate:filter(and(or(in(\"dt.entity.service\",entitySelector(\"type(service),entityName.equals(~\"di-ipv-cri-f2f-front~\")\")))))):limit(100):names"
      ]
    },
    {
      "name": "Frontend 5xx Errors",
      "tileType": "DATA_EXPLORER",
      "configured": true,
      "bounds": {
        "top": 988,
        "left": 1330,
        "width": 646,
        "height": 304
      },
      "tileFilter": {},
      "isAutoRefreshDisabled": false,
      "customName": "Data explorer results",
      "queries": [
        {
          "id": "C",
          "spaceAggregation": "AUTO",
          "timeAggregation": "DEFAULT",
          "splitBy": [
            "dt.entity.service"
          ],
          "metricSelector": "builtin:service.errors.fivexx.rate:filter(and(or(in(\"dt.entity.service\",entitySelector(\"type(service),entityName.equals(~\"di-ipv-cri-f2f-front~\")\")))))",
          "rate": "NONE",
          "enabled": true
        }
      ],
      "visualConfig": {
        "type": "STACKED_COLUMN",
        "global": {},
        "rules": [
          {
            "matcher": "C:",
            "unitTransform": "auto",
            "valueFormat": "auto",
            "properties": {
              "color": "GREEN",
              "seriesType": "STACKED_COLUMN"
            },
            "seriesOverrides": []
          }
        ],
        "axes": {
          "xAxis": {
            "displayName": "",
            "visible": true
          },
          "yAxes": [
            {
              "displayName": "",
              "visible": true,
              "min": "AUTO",
              "max": "AUTO",
              "position": "LEFT",
              "queryIds": [
                "A"
              ],
              "defaultAxis": true
            },
            {
              "displayName": "",
              "visible": true,
              "min": "AUTO",
              "max": "AUTO",
              "position": "RIGHT",
              "queryIds": [
                "B",
                "C"
              ],
              "defaultAxis": true
            }
          ]
        },
        "heatmapSettings": {
          "yAxis": "VALUE"
        },
        "thresholds": [
          {
            "axisTarget": "LEFT",
            "rules": [
              {
                "color": "#7dc540"
              },
              {
                "color": "#f5d30f"
              },
              {
                "color": "#dc172a"
              }
            ],
            "visible": true
          }
        ],
        "tableSettings": {
          "hiddenColumns": []
        },
        "graphChartSettings": {
          "connectNulls": false
        },
        "honeycombSettings": {
          "showHive": true,
          "showLegend": true,
          "showLabels": false
        }
      },
      "queriesSettings": {
        "resolution": ""
      },
      "metricExpressions": [
        "resolution=null&(builtin:service.errors.fivexx.rate:filter(and(or(in(\"dt.entity.service\",entitySelector(\"type(service),entityName.equals(~\"di-ipv-cri-f2f-front~\")\")))))):limit(100):names"
      ]
    },
    {
      "name": "Frontend Requests",
      "tileType": "DATA_EXPLORER",
      "configured": true,
      "bounds": {
        "top": 380,
        "left": 1330,
        "width": 646,
        "height": 304
      },
      "tileFilter": {},
      "isAutoRefreshDisabled": false,
      "customName": "Data explorer results",
      "queries": [
        {
          "id": "A",
          "spaceAggregation": "AUTO",
          "timeAggregation": "DEFAULT",
          "splitBy": [
            "dt.entity.service"
          ],
          "metricSelector": "builtin:service.requestCount.total:filter(and(or(in(\"dt.entity.service\",entitySelector(\"type(service),entityName.equals(~\"di-ipv-cri-f2f-front~\")\")))))",
          "rate": "NONE",
          "enabled": true
        }
      ],
      "visualConfig": {
        "type": "STACKED_COLUMN",
        "global": {},
        "rules": [
          {
            "matcher": "A:",
            "unitTransform": "auto",
            "valueFormat": "auto",
            "properties": {
              "color": "ROYALBLUE",
              "seriesType": "STACKED_COLUMN"
            },
            "seriesOverrides": []
          }
        ],
        "axes": {
          "xAxis": {
            "displayName": "",
            "visible": true
          },
          "yAxes": [
            {
              "displayName": "",
              "visible": true,
              "min": "AUTO",
              "max": "AUTO",
              "position": "LEFT",
              "queryIds": [
                "A"
              ],
              "defaultAxis": true
            },
            {
              "displayName": "",
              "visible": true,
              "min": "AUTO",
              "max": "AUTO",
              "position": "RIGHT",
              "queryIds": [
                "B",
                "C"
              ],
              "defaultAxis": true
            }
          ]
        },
        "heatmapSettings": {
          "yAxis": "VALUE"
        },
        "thresholds": [
          {
            "axisTarget": "LEFT",
            "rules": [
              {
                "color": "#7dc540"
              },
              {
                "color": "#f5d30f"
              },
              {
                "color": "#dc172a"
              }
            ],
            "visible": true
          }
        ],
        "tableSettings": {
          "hiddenColumns": []
        },
        "graphChartSettings": {
          "connectNulls": false
        },
        "honeycombSettings": {
          "showHive": true,
          "showLegend": true,
          "showLabels": false
        }
      },
      "queriesSettings": {
        "resolution": ""
      },
      "metricExpressions": [
        "resolution=null&(builtin:service.requestCount.total:filter(and(or(in(\"dt.entity.service\",entitySelector(\"type(service),entityName.equals(~\"di-ipv-cri-f2f-front~\")\")))))):limit(100):names"
      ]
    },
    {
      "name": "Markdown",
      "tileType": "MARKDOWN",
      "configured": true,
      "bounds": {
        "top": 0,
        "left": 1330,
        "width": 342,
        "height": 38
      },
      "tileFilter": {},
      "isAutoRefreshDisabled": false,
      "markdown": "## [F2F ECS Metrics](https://bhe21058.live.dynatrace.com/#dashboard;gtf=-30d%20to%20now;gf=all;id=589dc88d-a778-4450-89e1-e7ef2c530f78)\n"
    },
    {
      "name": "Markdown",
      "tileType": "MARKDOWN",
      "configured": true,
      "bounds": {
        "top": 0,
        "left": 646,
        "width": 342,
        "height": 38
      },
      "tileFilter": {},
      "isAutoRefreshDisabled": false,
      "markdown": "## [F2F API Gateway Metrics](https://bhe21058.live.dynatrace.com/#dashboard;gtf=-30d%20to%20now;gf=all;id=ca31f3f1-f255-42b8-a77d-debc0068ec23)\n"
    },
    {
      "name": "Markdown",
      "tileType": "MARKDOWN",
      "configured": true,
      "bounds": {
        "top": 0,
        "left": 0,
        "width": 342,
        "height": 38
      },
      "tileFilter": {},
      "isAutoRefreshDisabled": false,
      "markdown": "## [F2F Lambda Metrics](https://bhe21058.live.dynatrace.com/#dashboard;gtf=-30d%20to%20now;gf=all;id=fbdcd6e2-f5f5-40d0-8aaa-2d91f5c9d636)"
    },
    {
      "name": "Backend Requests",
      "tileType": "DATA_EXPLORER",
      "configured": true,
      "bounds": {
        "top": 380,
        "left": 0,
        "width": 304,
        "height": 304
      },
      "tileFilter": {},
      "isAutoRefreshDisabled": false,
      "customName": "Data explorer results",
      "queries": [
        {
          "id": "A",
          "metric": "cloud.aws.apigateway.countByAccountIdApiNameRegion",
          "spaceAggregation": "SUM",
          "timeAggregation": "DEFAULT",
          "splitBy": [],
          "sortBy": "DESC",
          "sortByDimension": "",
          "filterBy": {
            "filterOperator": "AND",
            "nestedFilters": [
              {
                "filter": "apiname",
                "filterType": "DIMENSION",
                "filterOperator": "OR",
                "nestedFilters": [],
                "criteria": [
                  {
                    "value": "f2f-cri-api - F2F Credential Issuer Private API",
                    "evaluator": "EQ"
                  }
                ]
              }
            ],
            "criteria": []
          },
          "limit": 20,
          "rate": "NONE",
          "enabled": true
        }
      ],
      "visualConfig": {
        "type": "SINGLE_VALUE",
        "global": {},
        "rules": [
          {
            "matcher": "A:",
            "unitTransform": "auto",
            "valueFormat": "auto",
            "properties": {
              "color": "GREEN",
              "seriesType": "STACKED_COLUMN",
              "alias": "Request"
            },
            "seriesOverrides": [
              {
                "name": "f2f-cri-api - F2F Credential Issuer Private API",
                "color": "#14a8f5"
              },
              {
                "name": "Select series",
                "color": "#dc172a"
              },
              {
                "name": "Select series",
                "color": "#ffee7c"
              }
            ]
          }
        ],
        "axes": {
          "xAxis": {
            "visible": true
          },
          "yAxes": []
        },
        "heatmapSettings": {
          "yAxis": "VALUE"
        },
        "singleValueSettings": {
          "showTrend": true,
          "showSparkLine": true,
          "linkTileColorToThreshold": true
        },
        "thresholds": [
          {
            "axisTarget": "LEFT",
            "rules": [
              {
                "color": "#7dc540"
              },
              {
                "color": "#f5d30f"
              },
              {
                "color": "#dc172a"
              }
            ],
            "visible": true
          }
        ],
        "tableSettings": {
          "hiddenColumns": []
        },
        "graphChartSettings": {
          "connectNulls": false
        },
        "honeycombSettings": {
          "showHive": true,
          "showLegend": true,
          "showLabels": false
        }
      },
      "queriesSettings": {
        "resolution": ""
      },
      "metricExpressions": [
        "resolution=Inf&(cloud.aws.apigateway.countByAccountIdApiNameRegion:filter(and(or(eq(apiname,\"f2f-cri-api - F2F Credential Issuer Private API\")))):splitBy():sum:sort(value(sum,descending)):limit(20)):limit(100):names",
        "resolution=null&(cloud.aws.apigateway.countByAccountIdApiNameRegion:filter(and(or(eq(apiname,\"f2f-cri-api - F2F Credential Issuer Private API\")))):splitBy():sum:sort(value(sum,descending)):limit(20))"
      ]
    },
    {
      "name": "Backend Requests",
      "tileType": "DATA_EXPLORER",
      "configured": true,
      "bounds": {
        "top": 380,
        "left": 304,
        "width": 722,
        "height": 304
      },
      "tileFilter": {},
      "isAutoRefreshDisabled": false,
      "customName": "Data explorer results",
      "queries": [
        {
          "id": "A",
          "metric": "cloud.aws.apigateway.countByAccountIdApiNameRegion",
          "spaceAggregation": "SUM",
          "timeAggregation": "DEFAULT",
          "splitBy": [],
          "sortBy": "DESC",
          "sortByDimension": "",
          "filterBy": {
            "filterOperator": "AND",
            "nestedFilters": [
              {
                "filter": "apiname",
                "filterType": "DIMENSION",
                "filterOperator": "OR",
                "nestedFilters": [],
                "criteria": [
                  {
                    "value": "f2f-cri-api - F2F Credential Issuer Private API",
                    "evaluator": "EQ"
                  }
                ]
              }
            ],
            "criteria": []
          },
          "limit": 20,
          "rate": "NONE",
          "enabled": true
        }
      ],
      "visualConfig": {
        "type": "STACKED_COLUMN",
        "global": {},
        "rules": [
          {
            "matcher": "A:",
            "unitTransform": "auto",
            "valueFormat": "auto",
            "properties": {
              "color": "GREEN",
              "seriesType": "STACKED_COLUMN"
            },
            "seriesOverrides": []
          }
        ],
        "axes": {
          "xAxis": {
            "displayName": "",
            "visible": true
          },
          "yAxes": [
            {
              "displayName": "",
              "visible": true,
              "min": "AUTO",
              "max": "AUTO",
              "position": "LEFT",
              "queryIds": [
                "A"
              ],
              "defaultAxis": true
            }
          ]
        },
        "heatmapSettings": {
          "yAxis": "VALUE"
        },
        "thresholds": [
          {
            "axisTarget": "LEFT",
            "rules": [
              {
                "color": "#7dc540"
              },
              {
                "color": "#f5d30f"
              },
              {
                "color": "#dc172a"
              }
            ],
            "visible": true
          }
        ],
        "tableSettings": {
          "hiddenColumns": []
        },
        "graphChartSettings": {
          "connectNulls": false
        },
        "honeycombSettings": {
          "showHive": true,
          "showLegend": true,
          "showLabels": false
        }
      },
      "queriesSettings": {
        "resolution": ""
      },
      "metricExpressions": [
        "resolution=null&(cloud.aws.apigateway.countByAccountIdApiNameRegion:filter(and(or(eq(apiname,\"f2f-cri-api - F2F Credential Issuer Private API\")))):splitBy():sum:sort(value(sum,descending)):limit(20)):limit(100):names"
      ]
    },
    {
      "name": "Backend 4XX Error",
      "tileType": "DATA_EXPLORER",
      "configured": true,
      "bounds": {
        "top": 684,
        "left": 0,
        "width": 304,
        "height": 304
      },
      "tileFilter": {},
      "isAutoRefreshDisabled": false,
      "customName": "Data explorer results",
      "queries": [
        {
          "id": "A",
          "metric": "cloud.aws.apigateway.4xxErrorByAccountIdApiNameRegion",
          "spaceAggregation": "SUM",
          "timeAggregation": "DEFAULT",
          "splitBy": [],
          "sortBy": "DESC",
          "sortByDimension": "",
          "filterBy": {
            "filterOperator": "AND",
            "nestedFilters": [
              {
                "filter": "apiname",
                "filterType": "DIMENSION",
                "filterOperator": "OR",
                "nestedFilters": [],
                "criteria": [
                  {
                    "value": "f2f-cri-api - F2F Credential Issuer Private API",
                    "evaluator": "EQ"
                  }
                ]
              }
            ],
            "criteria": []
          },
          "limit": 20,
          "rate": "NONE",
          "enabled": true
        }
      ],
      "visualConfig": {
        "type": "SINGLE_VALUE",
        "global": {},
        "rules": [
          {
            "matcher": "A:",
            "unitTransform": "auto",
            "valueFormat": "auto",
            "properties": {
              "color": "GREEN",
              "seriesType": "STACKED_COLUMN"
            },
            "seriesOverrides": [
              {
                "name": "f2f-cri-api - F2F Credential Issuer Private API",
                "color": "#fd8232"
              },
              {
                "name": "Select series",
                "color": "#5ead35"
              },
              {
                "name": "Select series",
                "color": "#14a8f5"
              }
            ]
          }
        ],
        "axes": {
          "xAxis": {
            "visible": true
          },
          "yAxes": []
        },
        "heatmapSettings": {
          "yAxis": "VALUE"
        },
        "singleValueSettings": {
          "showTrend": true,
          "showSparkLine": true,
          "linkTileColorToThreshold": true
        },
        "thresholds": [
          {
            "axisTarget": "LEFT",
            "rules": [
              {
                "color": "#7dc540"
              },
              {
                "color": "#f5d30f"
              },
              {
                "color": "#dc172a"
              }
            ],
            "visible": true
          }
        ],
        "tableSettings": {
          "hiddenColumns": []
        },
        "graphChartSettings": {
          "connectNulls": false
        },
        "honeycombSettings": {
          "showHive": true,
          "showLegend": true,
          "showLabels": false
        }
      },
      "queriesSettings": {
        "resolution": ""
      },
      "metricExpressions": [
        "resolution=Inf&(cloud.aws.apigateway.\"4xxErrorByAccountIdApiNameRegion\":filter(and(or(eq(apiname,\"f2f-cri-api - F2F Credential Issuer Private API\")))):splitBy():sum:sort(value(sum,descending)):limit(20)):limit(100):names",
        "resolution=null&(cloud.aws.apigateway.\"4xxErrorByAccountIdApiNameRegion\":filter(and(or(eq(apiname,\"f2f-cri-api - F2F Credential Issuer Private API\")))):splitBy():sum:sort(value(sum,descending)):limit(20))"
      ]
    },
    {
      "name": "Backend 4xx Errors",
      "tileType": "DATA_EXPLORER",
      "configured": true,
      "bounds": {
        "top": 684,
        "left": 304,
        "width": 722,
        "height": 304
      },
      "tileFilter": {},
      "isAutoRefreshDisabled": false,
      "customName": "Data explorer results",
      "queries": [
        {
          "id": "B",
          "metric": "cloud.aws.apigateway.4xxErrorByAccountIdApiNameRegion",
          "spaceAggregation": "SUM",
          "timeAggregation": "DEFAULT",
          "splitBy": [],
          "sortBy": "DESC",
          "sortByDimension": "",
          "filterBy": {
            "filterOperator": "AND",
            "nestedFilters": [
              {
                "filter": "apiname",
                "filterType": "DIMENSION",
                "filterOperator": "OR",
                "nestedFilters": [],
                "criteria": [
                  {
                    "value": "f2f-cri-api - F2F Credential Issuer Private API",
                    "evaluator": "EQ"
                  }
                ]
              }
            ],
            "criteria": []
          },
          "limit": 20,
          "rate": "NONE",
          "enabled": true
        }
      ],
      "visualConfig": {
        "type": "STACKED_COLUMN",
        "global": {},
        "rules": [
          {
            "matcher": "B:",
            "unitTransform": "auto",
            "valueFormat": "auto",
            "properties": {
              "color": "YELLOW",
              "seriesType": "STACKED_COLUMN"
            },
            "seriesOverrides": []
          }
        ],
        "axes": {
          "xAxis": {
            "displayName": "",
            "visible": true
          },
          "yAxes": [
            {
              "displayName": "",
              "visible": true,
              "min": "AUTO",
              "max": "AUTO",
              "position": "LEFT",
              "queryIds": [
                "B"
              ],
              "defaultAxis": true
            }
          ]
        },
        "heatmapSettings": {
          "yAxis": "VALUE"
        },
        "thresholds": [
          {
            "axisTarget": "LEFT",
            "rules": [
              {
                "color": "#7dc540"
              },
              {
                "color": "#f5d30f"
              },
              {
                "color": "#dc172a"
              }
            ],
            "visible": true
          }
        ],
        "tableSettings": {
          "hiddenColumns": []
        },
        "graphChartSettings": {
          "connectNulls": false
        },
        "honeycombSettings": {
          "showHive": true,
          "showLegend": true,
          "showLabels": false
        }
      },
      "queriesSettings": {
        "resolution": ""
      },
      "metricExpressions": [
        "resolution=null&(cloud.aws.apigateway.\"4xxErrorByAccountIdApiNameRegion\":filter(and(or(eq(apiname,\"f2f-cri-api - F2F Credential Issuer Private API\")))):splitBy():sum:sort(value(sum,descending)):limit(20)):limit(100):names"
      ]
    },
    {
      "name": "Backend 5XX Errors",
      "tileType": "DATA_EXPLORER",
      "configured": true,
      "bounds": {
        "top": 988,
        "left": 0,
        "width": 304,
        "height": 304
      },
      "tileFilter": {},
      "isAutoRefreshDisabled": false,
      "customName": "Data explorer results",
      "queries": [
        {
          "id": "A",
          "metric": "cloud.aws.apigateway.5xxErrorByAccountIdApiNameRegion",
          "spaceAggregation": "SUM",
          "timeAggregation": "DEFAULT",
          "splitBy": [],
          "sortBy": "DESC",
          "sortByDimension": "",
          "filterBy": {
            "filterOperator": "AND",
            "nestedFilters": [
              {
                "filter": "apiname",
                "filterType": "DIMENSION",
                "filterOperator": "OR",
                "nestedFilters": [],
                "criteria": [
                  {
                    "value": "f2f-cri-api - F2F Credential Issuer Private API",
                    "evaluator": "EQ"
                  }
                ]
              }
            ],
            "criteria": []
          },
          "limit": 20,
          "rate": "NONE",
          "enabled": true
        }
      ],
      "visualConfig": {
        "type": "SINGLE_VALUE",
        "global": {},
        "rules": [
          {
            "matcher": "A:",
            "unitTransform": "auto",
            "valueFormat": "auto",
            "properties": {
              "color": "GREEN",
              "seriesType": "STACKED_COLUMN"
            },
            "seriesOverrides": [
              {
                "name": "f2f-cri-api - F2F Credential Issuer Private API",
                "color": "#c9a000"
              },
              {
                "name": "Select series",
                "color": "#1f7e1e"
              },
              {
                "name": "Select series",
                "color": "#93060e"
              }
            ]
          }
        ],
        "axes": {
          "xAxis": {
            "visible": true
          },
          "yAxes": []
        },
        "heatmapSettings": {
          "yAxis": "VALUE"
        },
        "singleValueSettings": {
          "showTrend": true,
          "showSparkLine": true,
          "linkTileColorToThreshold": true
        },
        "thresholds": [
          {
            "axisTarget": "LEFT",
            "rules": [
              {
                "color": "#7dc540"
              },
              {
                "color": "#f5d30f"
              },
              {
                "color": "#dc172a"
              }
            ],
            "visible": true
          }
        ],
        "tableSettings": {
          "hiddenColumns": []
        },
        "graphChartSettings": {
          "connectNulls": false
        },
        "honeycombSettings": {
          "showHive": true,
          "showLegend": true,
          "showLabels": false
        }
      },
      "queriesSettings": {
        "resolution": ""
      },
      "metricExpressions": [
        "resolution=Inf&(cloud.aws.apigateway.\"5xxErrorByAccountIdApiNameRegion\":filter(and(or(eq(apiname,\"f2f-cri-api - F2F Credential Issuer Private API\")))):splitBy():sum:sort(value(sum,descending)):limit(20)):limit(100):names",
        "resolution=null&(cloud.aws.apigateway.\"5xxErrorByAccountIdApiNameRegion\":filter(and(or(eq(apiname,\"f2f-cri-api - F2F Credential Issuer Private API\")))):splitBy():sum:sort(value(sum,descending)):limit(20))"
      ]
    },
    {
      "name": "Backend 5xx Errors",
      "tileType": "DATA_EXPLORER",
      "configured": true,
      "bounds": {
        "top": 988,
        "left": 304,
        "width": 722,
        "height": 304
      },
      "tileFilter": {},
      "isAutoRefreshDisabled": false,
      "customName": "Data explorer results",
      "queries": [
        {
          "id": "C",
          "metric": "cloud.aws.apigateway.5xxErrorByAccountIdApiNameRegion",
          "spaceAggregation": "SUM",
          "timeAggregation": "DEFAULT",
          "splitBy": [],
          "sortBy": "DESC",
          "sortByDimension": "",
          "filterBy": {
            "filterOperator": "AND",
            "nestedFilters": [
              {
                "filter": "apiname",
                "filterType": "DIMENSION",
                "filterOperator": "OR",
                "nestedFilters": [],
                "criteria": [
                  {
                    "value": "f2f-cri-api - F2F Credential Issuer Private API",
                    "evaluator": "EQ"
                  }
                ]
              }
            ],
            "criteria": []
          },
          "limit": 20,
          "rate": "NONE",
          "enabled": true
        }
      ],
      "visualConfig": {
        "type": "STACKED_COLUMN",
        "global": {},
        "rules": [
          {
            "matcher": "C:",
            "unitTransform": "auto",
            "valueFormat": "auto",
            "properties": {
              "color": "TURQUOISE",
              "seriesType": "STACKED_COLUMN"
            },
            "seriesOverrides": []
          }
        ],
        "axes": {
          "xAxis": {
            "displayName": "",
            "visible": true
          },
          "yAxes": [
            {
              "displayName": "",
              "visible": true,
              "min": "AUTO",
              "max": "AUTO",
              "position": "LEFT",
              "queryIds": [
                "C"
              ],
              "defaultAxis": true
            }
          ]
        },
        "heatmapSettings": {
          "yAxis": "VALUE"
        },
        "thresholds": [
          {
            "axisTarget": "LEFT",
            "rules": [
              {
                "color": "#7dc540"
              },
              {
                "color": "#f5d30f"
              },
              {
                "color": "#dc172a"
              }
            ],
            "visible": true
          }
        ],
        "tableSettings": {
          "hiddenColumns": []
        },
        "graphChartSettings": {
          "connectNulls": false
        },
        "honeycombSettings": {
          "showHive": true,
          "showLegend": true,
          "showLabels": false
        }
      },
      "queriesSettings": {
        "resolution": ""
      },
      "metricExpressions": [
        "resolution=null&(cloud.aws.apigateway.\"5xxErrorByAccountIdApiNameRegion\":filter(and(or(eq(apiname,\"f2f-cri-api - F2F Credential Issuer Private API\")))):splitBy():sum:sort(value(sum,descending)):limit(20)):limit(100):names"
      ]
    },
    {
      "name": "CPU Utilisation",
      "tileType": "DATA_EXPLORER",
      "configured": true,
      "bounds": {
        "top": 1292,
        "left": 0,
        "width": 304,
        "height": 304
      },
      "tileFilter": {},
      "isAutoRefreshDisabled": false,
      "customName": "Data explorer results",
      "queries": [
        {
          "id": "A",
          "metric": "cloud.aws.ecs.containerinsights.cpuUtilizedByAccountIdClusterNameRegionServiceName",
          "spaceAggregation": "AUTO",
          "timeAggregation": "DEFAULT",
          "splitBy": [],
          "sortBy": "DESC",
          "sortByDimension": "",
          "filterBy": {
            "filterOperator": "AND",
            "nestedFilters": [
              {
                "filter": "servicename",
                "filterType": "DIMENSION",
                "filterOperator": "OR",
                "nestedFilters": [],
                "criteria": [
                  {
                    "value": "f2f-cri-front-F2FFrontEcsService-L7mJP36tBhG6",
                    "evaluator": "EQ"
                  }
                ]
              }
            ],
            "criteria": []
          },
          "limit": 20,
          "rate": "NONE",
          "enabled": true
        }
      ],
      "visualConfig": {
        "type": "SINGLE_VALUE",
        "global": {},
        "rules": [
          {
            "matcher": "A:",
            "unitTransform": "auto",
            "valueFormat": "auto",
            "properties": {
              "color": "DEFAULT",
              "seriesType": "STACKED_AREA",
              "alias": "CPU Utilisation by Service"
            },
            "seriesOverrides": [
              {
                "name": "cic-cri-front-CICFrontEcsService-G7NkOt9sXyBp",
                "color": "#4556d7"
              },
              {
                "name": "ipvreturn-front-IPRFrontEcsService-7FAsrgigUrDQ",
                "color": "#ffe11c"
              },
              {
                "name": "f2f-cri-front-F2FFrontEcsService-L7mJP36tBhG6",
                "color": "#9cd575"
              }
            ]
          }
        ],
        "axes": {
          "xAxis": {
            "visible": true
          },
          "yAxes": []
        },
        "heatmapSettings": {
          "yAxis": "VALUE"
        },
        "singleValueSettings": {
          "showTrend": true,
          "showSparkLine": true,
          "linkTileColorToThreshold": true
        },
        "thresholds": [
          {
            "axisTarget": "LEFT",
            "columnId": "CpuUtilized (by ServiceName)",
            "rules": [
              {
                "color": "#7dc540"
              },
              {
                "color": "#f5d30f"
              },
              {
                "color": "#dc172a"
              }
            ],
            "queryId": "A",
            "visible": true
          }
        ],
        "tableSettings": {
          "hiddenColumns": [
            "A:ServiceName.name"
          ]
        },
        "graphChartSettings": {
          "connectNulls": false
        },
        "honeycombSettings": {
          "showHive": true,
          "showLegend": true,
          "showLabels": false
        }
      },
      "queriesSettings": {
        "resolution": ""
      },
      "metricExpressions": [
        "resolution=Inf&(cloud.aws.ecs.containerinsights.cpuUtilizedByAccountIdClusterNameRegionServiceName:filter(and(or(eq(servicename,f2f-cri-front-F2FFrontEcsService-L7mJP36tBhG6)))):splitBy():sort(value(auto,descending)):limit(20)):limit(100):names",
        "resolution=null&(cloud.aws.ecs.containerinsights.cpuUtilizedByAccountIdClusterNameRegionServiceName:filter(and(or(eq(servicename,f2f-cri-front-F2FFrontEcsService-L7mJP36tBhG6)))):splitBy():sort(value(auto,descending)):limit(20))"
      ]
    },
    {
      "name": "CPU Utilisation",
      "tileType": "DATA_EXPLORER",
      "configured": true,
      "bounds": {
        "top": 1292,
        "left": 304,
        "width": 722,
        "height": 304
      },
      "tileFilter": {},
      "isAutoRefreshDisabled": false,
      "customName": "Data explorer results",
      "queries": [
        {
          "id": "A",
          "metric": "cloud.aws.ecs.containerinsights.cpuUtilizedByAccountIdClusterNameRegionServiceName",
          "spaceAggregation": "AUTO",
          "timeAggregation": "DEFAULT",
          "splitBy": [],
          "sortBy": "DESC",
          "sortByDimension": "",
          "filterBy": {
            "filterOperator": "AND",
            "nestedFilters": [
              {
                "filter": "servicename",
                "filterType": "DIMENSION",
                "filterOperator": "OR",
                "nestedFilters": [],
                "criteria": [
                  {
                    "value": "f2f-cri-front-F2FFrontEcsService-L7mJP36tBhG6",
                    "evaluator": "EQ"
                  }
                ]
              }
            ],
            "criteria": []
          },
          "limit": 20,
          "rate": "NONE",
          "enabled": true
        }
      ],
      "visualConfig": {
        "type": "STACKED_AREA",
        "global": {},
        "rules": [
          {
            "matcher": "A:",
            "unitTransform": "auto",
            "valueFormat": "auto",
            "properties": {
              "color": "DEFAULT",
              "seriesType": "STACKED_AREA",
              "alias": "CPU Utilisation by Service"
            },
            "seriesOverrides": [
              {
                "name": "Select series",
                "color": "#4556d7"
              },
              {
                "name": "Select series",
                "color": "#ffe11c"
              },
              {
                "name": "Select series",
                "color": "#9cd575"
              }
            ]
          }
        ],
        "axes": {
          "xAxis": {
            "displayName": "",
            "visible": true
          },
          "yAxes": [
            {
              "displayName": "",
              "visible": true,
              "min": "AUTO",
              "max": "AUTO",
              "position": "LEFT",
              "queryIds": [
                "A"
              ],
              "defaultAxis": true
            }
          ]
        },
        "heatmapSettings": {
          "yAxis": "VALUE"
        },
        "thresholds": [
          {
            "axisTarget": "LEFT",
            "columnId": "MemoryUtilization (by ServiceName)",
            "rules": [
              {
                "color": "#7dc540"
              },
              {
                "color": "#f5d30f"
              },
              {
                "color": "#dc172a"
              }
            ],
            "queryId": "A",
            "visible": true
          }
        ],
        "tableSettings": {
          "hiddenColumns": []
        },
        "graphChartSettings": {
          "connectNulls": false
        },
        "honeycombSettings": {
          "showHive": true,
          "showLegend": true,
          "showLabels": false
        }
      },
      "queriesSettings": {
        "resolution": ""
      },
      "metricExpressions": [
        "resolution=null&(cloud.aws.ecs.containerinsights.cpuUtilizedByAccountIdClusterNameRegionServiceName:filter(and(or(eq(servicename,f2f-cri-front-F2FFrontEcsService-L7mJP36tBhG6)))):splitBy():sort(value(auto,descending)):limit(20)):limit(100):names"
      ]
    },
    {
      "name": "Memory Utilisation",
      "tileType": "DATA_EXPLORER",
      "configured": true,
      "bounds": {
        "top": 1292,
        "left": 1026,
        "width": 304,
        "height": 304
      },
      "tileFilter": {},
      "isAutoRefreshDisabled": false,
      "customName": "Data explorer results",
      "queries": [
        {
          "id": "A",
          "metric": "cloud.aws.ecs.containerinsights.memoryUtilizedByAccountIdClusterNameRegionServiceName",
          "spaceAggregation": "AUTO",
          "timeAggregation": "DEFAULT",
          "splitBy": [],
          "sortBy": "DESC",
          "sortByDimension": "",
          "filterBy": {
            "filterOperator": "AND",
            "nestedFilters": [
              {
                "filter": "servicename",
                "filterType": "DIMENSION",
                "filterOperator": "OR",
                "nestedFilters": [],
                "criteria": [
                  {
                    "value": "f2f-cri-front-F2FFrontEcsService-L7mJP36tBhG6",
                    "evaluator": "EQ"
                  }
                ]
              }
            ],
            "criteria": []
          },
          "limit": 20,
          "rate": "NONE",
          "enabled": true
        }
      ],
      "visualConfig": {
        "type": "SINGLE_VALUE",
        "global": {},
        "rules": [
          {
            "matcher": "A:",
            "unitTransform": "auto",
            "valueFormat": "auto",
            "properties": {
              "color": "DEFAULT",
              "seriesType": "LINE",
              "alias": "CPU Utilisation by Service"
            },
            "seriesOverrides": [
              {
                "name": "Select series",
                "color": "#ef651f"
              },
              {
                "name": "Select series",
                "color": "#ffee7c"
              },
              {
                "name": "f2f-cri-front-F2FFrontEcsService-L7mJP36tBhG6",
                "color": "#006bba"
              }
            ]
          }
        ],
        "axes": {
          "xAxis": {
            "visible": true
          },
          "yAxes": []
        },
        "heatmapSettings": {
          "yAxis": "VALUE"
        },
        "singleValueSettings": {
          "showTrend": true,
          "showSparkLine": true,
          "linkTileColorToThreshold": true
        },
        "thresholds": [
          {
            "axisTarget": "LEFT",
            "columnId": "MemoryUtilization (by ServiceName)",
            "rules": [
              {
                "color": "#7dc540"
              },
              {
                "color": "#f5d30f"
              },
              {
                "color": "#dc172a"
              }
            ],
            "queryId": "A",
            "visible": true
          }
        ],
        "tableSettings": {
          "hiddenColumns": []
        },
        "graphChartSettings": {
          "connectNulls": false
        },
        "honeycombSettings": {
          "showHive": true,
          "showLegend": true,
          "showLabels": false
        }
      },
      "queriesSettings": {
        "resolution": ""
      },
      "metricExpressions": [
        "resolution=Inf&(cloud.aws.ecs.containerinsights.memoryUtilizedByAccountIdClusterNameRegionServiceName:filter(and(or(eq(servicename,f2f-cri-front-F2FFrontEcsService-L7mJP36tBhG6)))):splitBy():sort(value(auto,descending)):limit(20)):limit(100):names",
        "resolution=null&(cloud.aws.ecs.containerinsights.memoryUtilizedByAccountIdClusterNameRegionServiceName:filter(and(or(eq(servicename,f2f-cri-front-F2FFrontEcsService-L7mJP36tBhG6)))):splitBy():sort(value(auto,descending)):limit(20))"
      ]
    },
    {
      "name": "Memory Utilisation",
      "tileType": "DATA_EXPLORER",
      "configured": true,
      "bounds": {
        "top": 1292,
        "left": 1330,
        "width": 646,
        "height": 304
      },
      "tileFilter": {},
      "isAutoRefreshDisabled": false,
      "customName": "Data explorer results",
      "queries": [
        {
          "id": "A",
          "metric": "cloud.aws.ecs.containerinsights.memoryUtilizedByAccountIdClusterNameRegionServiceName",
          "spaceAggregation": "AUTO",
          "timeAggregation": "DEFAULT",
          "splitBy": [],
          "sortBy": "DESC",
          "sortByDimension": "",
          "filterBy": {
            "filterOperator": "AND",
            "nestedFilters": [
              {
                "filter": "servicename",
                "filterType": "DIMENSION",
                "filterOperator": "OR",
                "nestedFilters": [],
                "criteria": [
                  {
                    "value": "f2f-cri-front-F2FFrontEcsService-L7mJP36tBhG6",
                    "evaluator": "EQ"
                  }
                ]
              }
            ],
            "criteria": []
          },
          "limit": 20,
          "rate": "NONE",
          "enabled": true
        }
      ],
      "visualConfig": {
        "type": "GRAPH_CHART",
        "global": {},
        "rules": [
          {
            "matcher": "A:",
            "unitTransform": "auto",
            "valueFormat": "auto",
            "properties": {
              "color": "DEFAULT",
              "seriesType": "LINE",
              "alias": "CPU Utilisation by Service"
            },
            "seriesOverrides": [
              {
                "name": "Select series",
                "color": "#ef651f"
              },
              {
                "name": "Select series",
                "color": "#ffee7c"
              },
              {
                "name": "Select series",
                "color": "#006bba"
              }
            ]
          }
        ],
        "axes": {
          "xAxis": {
            "displayName": "",
            "visible": true
          },
          "yAxes": [
            {
              "displayName": "",
              "visible": true,
              "min": "AUTO",
              "max": "AUTO",
              "position": "LEFT",
              "queryIds": [
                "A"
              ],
              "defaultAxis": true
            }
          ]
        },
        "heatmapSettings": {
          "yAxis": "VALUE"
        },
        "thresholds": [
          {
            "axisTarget": "LEFT",
            "columnId": "MemoryUtilization (by ServiceName)",
            "rules": [
              {
                "color": "#7dc540"
              },
              {
                "color": "#f5d30f"
              },
              {
                "color": "#dc172a"
              }
            ],
            "queryId": "A",
            "visible": true
          }
        ],
        "tableSettings": {
          "hiddenColumns": []
        },
        "graphChartSettings": {
          "connectNulls": false
        },
        "honeycombSettings": {
          "showHive": true,
          "showLegend": true,
          "showLabels": false
        }
      },
      "queriesSettings": {
        "resolution": ""
      },
      "metricExpressions": [
        "resolution=null&(cloud.aws.ecs.containerinsights.memoryUtilizedByAccountIdClusterNameRegionServiceName:filter(and(or(eq(servicename,f2f-cri-front-F2FFrontEcsService-L7mJP36tBhG6)))):splitBy():sort(value(auto,descending)):limit(20)):limit(100):names"
      ]
    }
  ]
}
